[
  {
    "number": "A.17",
    "title": "Aeronautical knowledge test: §§ 61.35(a)(1) and 61.309.",
    "section": {
      "id": "additional-student-pilot",
      "title": "SPORT OR RECREATIONAL PILOT CERTIFICATES"
    },
    "farReference": "§ 61.309. I have determined that ",
    "endorsementText": "I certify that [First name, MI, Last name] has received the required aeronautical knowledge training of § 61.309. I have determined that [he or she] is prepared for the [name of] knowledge test.",
    "category": "Additional Endorsements",
    "expires": false,
    "lines": [
      "A.17 \tAeronautical knowledge test: §§ 61.35(a)(1) and 61.309.",
      "I certify that [First name, MI, Last name] has received the required aeronautical",
      "knowledge training of § 61.309. I have determined that [he or she] is prepared for the",
      "[name of] knowledge test."
    ]
  },
  {
    "number": "A.18",
    "title": "Taking flight proficiency check for different category or class of aircraft: §§ 61.309",
    "section": {
      "id": "additional-student-pilot",
      "title": "SPORT OR RECREATIONAL PILOT CERTIFICATES"
    },
    "farReference": "§ 61.309 and 61.311 and have determined that ",
    "endorsementText": "I certify that [First name, MI, Last name] has received the required training required in accordance with §§ 61.309 and 61.311 and have determined that [he or she] is prepared for the [name of] proficiency check.",
    "category": "Additional Endorsements",
    "expires": false,
    "lines": [
      "A.18 \tTaking flight proficiency check for different category or class of aircraft: §§ 61.309",
      "I certify that [First name, MI, Last name] has received the required training required in",
      "accordance with §§ 61.309 and 61.311 and have determined that [he or she] is prepared",
      "for the [name of] proficiency check."
    ]
  },
  {
    "number": "A.19",
    "title": "Passing flight proficiency check for different category or class of aircraft: §§ 61.309",
    "section": {
      "id": "additional-student-pilot",
      "title": "SPORT OR RECREATIONAL PILOT CERTIFICATES"
    },
    "farReference": "§ 61.309 and",
    "endorsementText": "I certify that [First name, MI, Last name] has met the requirements of §§ 61.309 and 61.311 and I have determined [him or her] proficient to act as pilot in command of [category and class] of light-sport aircraft.",
    "category": "Additional Endorsements",
    "expires": false,
    "lines": [
      "A.19 \tPassing flight proficiency check for different category or class of aircraft: §§ 61.309",
      "I certify that [First name, MI, Last name] has met the requirements of §§ 61.309 and",
      "61.311 and I have determined [him or her] proficient to act as pilot in command of",
      "[category and class] of light-sport aircraft."
    ]
  },
  {
    "number": "A.20",
    "title": "Taking sport pilot practical test: §§ 61.309, 61.311, and 61.313.",
    "section": {
      "id": "additional-student-pilot",
      "title": "SPORT OR RECREATIONAL PILOT CERTIFICATES"
    },
    "farReference": "§ 61.309 and 61.311 and met the aeronautical experience requirements of ",
    "endorsementText": "I certify that [First name, MI, Last name] has received the training required in accordance with §§ 61.309 and 61.311 and met the aeronautical experience requirements of § 61.313. I have determined that [he or she] is prepared for the [type of] practical test. Note: The endorsement for a practical test is required in addition to the § 61.39 endorsements provided in endorsements 1 and 2 (see paragraphs A.1 and A.2).",
    "category": "Additional Endorsements",
    "expires": false,
    "lines": [
      "A.20 \tTaking sport pilot practical test: §§ 61.309, 61.311, and 61.313.",
      "I certify that [First name, MI, Last name] has received the training required in accordance",
      "with §§ 61.309 and 61.311 and met the aeronautical experience requirements of § 61.313.",
      "I have determined that [he or she] is prepared for the [type of] practical test.",
      "Note: The endorsement for a practical test is required in addition to the § 61.39",
      "endorsements provided in endorsements 1 and 2 (see paragraphs A.1 and A.2)."
    ]
  },
  {
    "number": "A.21",
    "title": "Passing a sport pilot practical test: §§ 61.309, 61.311, and 61.313. This endorsement is",
    "section": {
      "id": "additional-student-pilot",
      "title": "SPORT OR RECREATIONAL PILOT CERTIFICATES"
    },
    "farReference": "§ 61.317 and is issued by a Sport Pilot Examiner (SPE).",
    "endorsementText": "I certify that [First name, MI, Last name] has met the requirements of §§ 61.309, 61.311, and 61.313, and I have determined [him or her] proficient to act as pilot in command of [category and class of] light-sport aircraft. /s/ [date] S. P. Examiner 987654321 Exp. 12-31-19 -- 4 of 18 -- 8/27/18 \tAC 61-65H Appendix A A-10",
    "category": "Additional Endorsements",
    "expires": false,
    "lines": [
      "A.21 \tPassing a sport pilot practical test: §§ 61.309, 61.311, and 61.313. This endorsement is",
      "I certify that [First name, MI, Last name] has met the requirements of §§ 61.309, 61.311,",
      "and 61.313, and I have determined [him or her] proficient to act as pilot in command of",
      "[category and class of] light-sport aircraft.",
      "/s/ [date] S. P. Examiner 987654321 Exp. 12-31-19",
      "-- 4 of 18 --",
      "8/27/18 \tAC 61-65H",
      "Appendix A",
      "A-10"
    ]
  },
  {
    "number": "A.22",
    "title": "Class B, C, or D airspace, at an airport located in Class B, C, or D airspace, or to,",
    "section": {
      "id": "additional-student-pilot",
      "title": "SPORT OR RECREATIONAL PILOT CERTIFICATES"
    },
    "farReference": "§ 61.325.",
    "endorsementText": "I certify that [First name, MI, Last name] has received the required training of § 61.325. I have determined [he or she] is proficient to conduct operations in Class B, C, or D airspace, at an airport located in Class B, C, or D airspace, or to, from, through, or at an airport having an operational control tower.",
    "category": "Additional Endorsements",
    "expires": false,
    "lines": [
      "A.22 \tClass B, C, or D airspace, at an airport located in Class B, C, or D airspace, or to,",
      "I certify that [First name, MI, Last name] has received the required training of § 61.325.",
      "I have determined [he or she] is proficient to conduct operations in Class B, C, or D",
      "airspace, at an airport located in Class B, C, or D airspace, or to, from, through, or at an",
      "airport having an operational control tower."
    ]
  },
  {
    "number": "A.23",
    "title": "Light-sport aircraft that has a maximum speed in level flight with maximum",
    "section": {
      "id": "additional-student-pilot",
      "title": "SPORT OR RECREATIONAL PILOT CERTIFICATES"
    },
    "farReference": "§ 61.327.",
    "endorsementText": "I certify that [First name, MI, Last name] has received the required training required in accordance with § 61.327(a) in a [make and model] aircraft. I have determined [him or her] proficient to act as pilot in command of a light-sport aircraft that has a VH less than or equal to 87 KCAS.",
    "category": "Additional Endorsements",
    "expires": false,
    "lines": [
      "A.23 \tLight-sport aircraft that has a maximum speed in level flight with maximum",
      "I certify that [First name, MI, Last name] has received the required training required in",
      "accordance with § 61.327(a) in a [make and model] aircraft. I have determined [him or",
      "her] proficient to act as pilot in command of a light-sport aircraft that has a VH less than",
      "or equal to 87 KCAS."
    ]
  },
  {
    "number": "A.24",
    "title": "Light-sport aircraft that has a VH greater than 87 KCAS: § 61.327.",
    "section": {
      "id": "additional-student-pilot",
      "title": "SPORT OR RECREATIONAL PILOT CERTIFICATES"
    },
    "farReference": "§ 61.327(b) in a ",
    "endorsementText": "I certify that [First name, MI, Last name] has received the required training required in accordance with § 61.327(b) in a [make and model] aircraft. I have determined [him or her] proficient to act as pilot in command of a light-sport aircraft that has a VH greater than 87 KCAS.",
    "category": "Additional Endorsements",
    "expires": false,
    "lines": [
      "A.24 \tLight-sport aircraft that has a VH greater than 87 KCAS: § 61.327.",
      "I certify that [First name, MI, Last name] has received the required training required in",
      "accordance with § 61.327(b) in a [make and model] aircraft. I have determined [him or",
      "her] proficient to act as pilot in command of a light-sport aircraft that has a VH greater",
      "than 87 KCAS."
    ]
  },
  {
    "number": "A.25",
    "title": "Aeronautical knowledge test: §§ 61.35(a)(1), 61.96(b)(3), and 61.97(b).",
    "section": {
      "id": "additional-student-pilot",
      "title": "SPORT OR RECREATIONAL PILOT CERTIFICATES"
    },
    "farReference": "§ 61.97(b).",
    "endorsementText": "I certify that [First name, MI, Last name] has received the required training of § 61.97(b). I have determined that [he or she] is prepared for the [name of] knowledge test.",
    "category": "Additional Endorsements",
    "expires": false,
    "lines": [
      "A.25 \tAeronautical knowledge test: §§ 61.35(a)(1), 61.96(b)(3), and 61.97(b).",
      "I certify that [First name, MI, Last name] has received the required training of § 61.97(b).",
      "I have determined that [he or she] is prepared for the [name of] knowledge test."
    ]
  },
  {
    "number": "A.26",
    "title": "Flight proficiency/practical test: §§ 61.96(b)(5), 61.98(a) and (b), and 61.99. The",
    "section": {
      "id": "additional-student-pilot",
      "title": "SPORT OR RECREATIONAL PILOT CERTIFICATES"
    },
    "farReference": "§ 61.39 endorsements",
    "endorsementText": "I certify that [First name, MI, Last name] has received the required training of §§ 61.98(b) and 61.99. I have determined that [he or she] is prepared for the [name of] practical test.",
    "category": "Additional Endorsements",
    "expires": false,
    "lines": [
      "A.26 \tFlight proficiency/practical test: §§ 61.96(b)(5), 61.98(a) and (b), and 61.99. The",
      "I certify that [First name, MI, Last name] has received the required training of",
      "§§ 61.98(b) and 61.99. I have determined that [he or she] is prepared for the [name of]",
      "practical test."
    ]
  },
  {
    "number": "A.27",
    "title": "Recreational pilot to operate within 50 NM of the airport where training was",
    "section": {
      "id": "additional-student-pilot",
      "title": "SPORT OR RECREATIONAL PILOT CERTIFICATES"
    },
    "farReference": "§ 61.101(b).",
    "endorsementText": "I certify that [First name, MI, Last name] has received the required training of § 61.101(b). I have determined that [he or she] is competent to operate at the [name of airport]. -- 5 of 18 -- 8/27/18 \tAC 61-65H Appendix A A-11",
    "category": "Additional Endorsements",
    "expires": false,
    "lines": [
      "A.27 \tRecreational pilot to operate within 50 NM of the airport where training was",
      "I certify that [First name, MI, Last name] has received the required training of",
      "§ 61.101(b). I have determined that [he or she] is competent to operate at the [name of",
      "airport].",
      "-- 5 of 18 --",
      "8/27/18 \tAC 61-65H",
      "Appendix A",
      "A-11"
    ]
  },
  {
    "number": "A.28",
    "title": "Recreational pilot to act as pilot in command on a flight that exceeds 50 NM of the",
    "section": {
      "id": "additional-student-pilot",
      "title": "SPORT OR RECREATIONAL PILOT CERTIFICATES"
    },
    "farReference": "§ 61.101(c).",
    "endorsementText": "I certify that [First name, MI, Last name] has received the required cross-country training of § 61.101(c). I have determined that [he or she] is proficient in cross-country flying of part 61 subpart E.",
    "category": "Additional Endorsements",
    "expires": false,
    "lines": [
      "A.28 \tRecreational pilot to act as pilot in command on a flight that exceeds 50 NM of the",
      "I certify that [First name, MI, Last name] has received the required cross-country training",
      "of § 61.101(c). I have determined that [he or she] is proficient in cross-country flying of",
      "part 61 subpart E."
    ]
  },
  {
    "number": "A.29",
    "title": "Recreational pilot with less than 400 flight hours and no logged pilot in command",
    "section": {
      "id": "additional-student-pilot",
      "title": "SPORT OR RECREATIONAL PILOT CERTIFICATES"
    },
    "farReference": "§ 61.101(g).",
    "endorsementText": "I certify that [First name, MI, Last name] has received the required 180-day recurrent training of § 61.101(g) in a [make and model] aircraft. I have determined [him or her] proficient to act as pilot in command of that aircraft.",
    "category": "Additional Endorsements",
    "expires": false,
    "lines": [
      "A.29 \tRecreational pilot with less than 400 flight hours and no logged pilot in command",
      "I certify that [First name, MI, Last name] has received the required 180-day recurrent",
      "training of § 61.101(g) in a [make and model] aircraft. I have determined [him or her]",
      "proficient to act as pilot in command of that aircraft."
    ]
  },
  {
    "number": "A.30",
    "title": "Recreational pilot to conduct solo flights for the purpose of obtaining an additional",
    "section": {
      "id": "additional-student-pilot",
      "title": "SPORT OR RECREATIONAL PILOT CERTIFICATES"
    },
    "farReference": "§ 61.101(j).",
    "endorsementText": "I certify that [First name, MI, Last name] has received the required training of § 61.87 in a [make and model] aircraft. I have determined [he or she] is prepared to conduct a solo flight on [date] under the following conditions: [List all conditions which require endorsement (e.g., flight which requires communication with air traffic control, flight in an aircraft for which the pilot does not hold a category/class rating, etc.).]",
    "category": "Additional Endorsements",
    "expires": false,
    "lines": [
      "A.30 \tRecreational pilot to conduct solo flights for the purpose of obtaining an additional",
      "I certify that [First name, MI, Last name] has received the required training of § 61.87 in",
      "a [make and model] aircraft. I have determined [he or she] is prepared to conduct a solo",
      "flight on [date] under the following conditions: [List all conditions which require",
      "endorsement (e.g., flight which requires communication with air traffic control, flight in",
      "an aircraft for which the pilot does not hold a category/class rating, etc.).]"
    ]
  },
  {
    "number": "A.31",
    "title": "Class B, C, or D airspace, at an airport located in Class B, C, or D airspace, or to,",
    "section": {
      "id": "additional-student-pilot",
      "title": "SPORT OR RECREATIONAL PILOT CERTIFICATES"
    },
    "farReference": "§ 61.101(d).",
    "endorsementText": "I certify that [First name, MI, Last name] has received the required training of § 61.101(d). I have determined [he or she] is proficient to conduct operations in Class B, C, or D airspace, at an airport located in Class B, C, or D airspace, or to, from, through, or at an airport having an operational control tower.",
    "category": "Additional Endorsements",
    "expires": false,
    "lines": [
      "A.31 \tClass B, C, or D airspace, at an airport located in Class B, C, or D airspace, or to,",
      "I certify that [First name, MI, Last name] has received the required training of",
      "§ 61.101(d). I have determined [he or she] is proficient to conduct operations in Class B,",
      "C, or D airspace, at an airport located in Class B, C, or D airspace, or to, from, through,",
      "or at an airport having an operational control tower."
    ]
  },
  {
    "number": "A.32",
    "title": "Aeronautical knowledge test: §§ 61.35(a)(1), 61.103(d), and 61.105.",
    "section": {
      "id": "additional-student-pilot",
      "title": "SPORT OR RECREATIONAL PILOT CERTIFICATES"
    },
    "farReference": "§ 61.105. I have determined ",
    "endorsementText": "I certify that [First name, MI, Last name] has received the required training in accordance with § 61.105. I have determined [he or she] is prepared for the [name of] knowledge test.",
    "category": "Additional Endorsements",
    "expires": false,
    "lines": [
      "A.32 \tAeronautical knowledge test: §§ 61.35(a)(1), 61.103(d), and 61.105.",
      "I certify that [First name, MI, Last name] has received the required training in accordance",
      "with § 61.105. I have determined [he or she] is prepared for the [name of] knowledge",
      "test."
    ]
  },
  {
    "number": "A.33",
    "title": "Flight proficiency/practical test: §§ 61.103(f), 61.107(b), and 61.109. The endorsement",
    "section": {
      "id": "additional-student-pilot",
      "title": "SPORT OR RECREATIONAL PILOT CERTIFICATES"
    },
    "farReference": "§ 61.39 endorsements provided in",
    "endorsementText": "I certify that [First name, MI, Last name] has received the required training in accordance with §§ 61.107 and 61.109. I have determined [he or she] is prepared for the [name of] practical test. -- 6 of 18 -- 8/27/18 \tAC 61-65H Appendix A A-12",
    "category": "Additional Endorsements",
    "expires": false,
    "lines": [
      "A.33 \tFlight proficiency/practical test: §§ 61.103(f), 61.107(b), and 61.109. The endorsement",
      "I certify that [First name, MI, Last name] has received the required training in accordance",
      "with §§ 61.107 and 61.109. I have determined [he or she] is prepared for the [name of]",
      "practical test.",
      "-- 6 of 18 --",
      "8/27/18 \tAC 61-65H",
      "Appendix A",
      "A-12"
    ]
  },
  {
    "number": "A.34",
    "title": "Aeronautical knowledge test: §§ 61.35(a)(1), 61.123(c), and 61.125.",
    "section": {
      "id": "additional-student-pilot",
      "title": "SPORT OR RECREATIONAL PILOT CERTIFICATES"
    },
    "farReference": "§ 61.125.",
    "endorsementText": "I certify that [First name, MI, Last name] has received the required training of § 61.125. I have determined that [he or she] is prepared for the [name of] knowledge test.",
    "category": "Additional Endorsements",
    "expires": false,
    "lines": [
      "A.34 \tAeronautical knowledge test: §§ 61.35(a)(1), 61.123(c), and 61.125.",
      "I certify that [First name, MI, Last name] has received the required training of § 61.125.",
      "I have determined that [he or she] is prepared for the [name of] knowledge test."
    ]
  },
  {
    "number": "A.35",
    "title": "Flight proficiency/practical test: §§ 61.123(e), 61.127, and 61.129. The endorsement",
    "section": {
      "id": "additional-student-pilot",
      "title": "SPORT OR RECREATIONAL PILOT CERTIFICATES"
    },
    "farReference": "§ 61.39 endorsements provided in",
    "endorsementText": "I certify that [First name, MI, Last name] has received the required training of §§ 61.127 and 61.129. I have determined that [he or she] is prepared for the [name of] practical test. AIRLINE TRANSPORT PILOT (ATP) ENDORSEMENTS",
    "category": "Additional Endorsements",
    "expires": false,
    "lines": [
      "A.35 \tFlight proficiency/practical test: §§ 61.123(e), 61.127, and 61.129. The endorsement",
      "I certify that [First name, MI, Last name] has received the required training of §§ 61.127",
      "and 61.129. I have determined that [he or she] is prepared for the [name of] practical test.",
      "AIRLINE TRANSPORT PILOT (ATP) ENDORSEMENTS"
    ]
  },
  {
    "number": "A.36",
    "title": "Restricted privileges ATP Certificate, Airplane Multiengine Land (AMEL) rating:",
    "section": {
      "id": "additional-student-pilot",
      "title": "SPORT OR RECREATIONAL PILOT CERTIFICATES"
    },
    "farReference": "§ 61.160. This certifying statement can only be provided by an authorized institution of",
    "endorsementText": "",
    "category": "Additional Endorsements",
    "expires": false,
    "lines": [
      "A.36 \tRestricted privileges ATP Certificate, Airplane Multiengine Land (AMEL) rating:"
    ]
  },
  {
    "number": "A.37",
    "title": "ATP Certification Training Program (CTP): § 61.153(e). This endorsement is only",
    "section": {
      "id": "additional-student-pilot",
      "title": "SPORT OR RECREATIONAL PILOT CERTIFICATES"
    },
    "farReference": "§ 61.156. Refer to AC 61",
    "endorsementText": "",
    "category": "Additional Endorsements",
    "expires": false,
    "lines": [
      "A.37 \tATP Certification Training Program (CTP): § 61.153(e). This endorsement is only"
    ]
  },
  {
    "number": "A.38",
    "title": "Aeronautical knowledge test: §§ 61.35(a)(1) and 61.65(a) and (b).",
    "section": {
      "id": "additional-student-pilot",
      "title": "SPORT OR RECREATIONAL PILOT CERTIFICATES"
    },
    "farReference": "§ 61.65(b).",
    "endorsementText": "I certify that [First name, MI, Last name] has received the required training of § 61.65(b). I have determined that [he or she] is prepared for the Instrument–[airplane, helicopter, or powered-lift] knowledge test. -- 7 of 18 -- 8/27/18 \tAC 61-65H Appendix A A-13",
    "category": "Additional Endorsements",
    "expires": false,
    "lines": [
      "A.38 \tAeronautical knowledge test: §§ 61.35(a)(1) and 61.65(a) and (b).",
      "I certify that [First name, MI, Last name] has received the required training of § 61.65(b).",
      "I have determined that [he or she] is prepared for the Instrument–[airplane, helicopter, or",
      "powered-lift] knowledge test.",
      "-- 7 of 18 --",
      "8/27/18 \tAC 61-65H",
      "Appendix A",
      "A-13"
    ]
  },
  {
    "number": "A.39",
    "title": "Flight proficiency/practical test: § 61.65(a)(6).",
    "section": {
      "id": "additional-student-pilot",
      "title": "SPORT OR RECREATIONAL PILOT CERTIFICATES"
    },
    "farReference": "§ 61.65(c)",
    "endorsementText": "I certify that [First name, MI, Last name] has received the required training of § 61.65(c) and (d). I have determined [he or she] is prepared for the Instrument–[airplane, helicopter, or powered-lift] practical test.",
    "category": "Additional Endorsements",
    "expires": false,
    "lines": [
      "A.39 \tFlight proficiency/practical test: § 61.65(a)(6).",
      "I certify that [First name, MI, Last name] has received the required training of § 61.65(c)",
      "and (d). I have determined [he or she] is prepared for the Instrument–[airplane,",
      "helicopter, or powered-lift] practical test."
    ]
  },
  {
    "number": "A.40",
    "title": "Prerequisites for instrument practical tests: § 61.39(a).",
    "section": {
      "id": "additional-student-pilot",
      "title": "SPORT OR RECREATIONAL PILOT CERTIFICATES"
    },
    "farReference": "§ 61.39(a) in preparation for the practical test within 2 calendar",
    "endorsementText": "I certify that [First name, MI, Last name] has received and logged the required flight time/training of § 61.39(a) in preparation for the practical test within 2 calendar-months preceding the date of the test and has satisfactory knowledge of the subject areas in which [he or she] was shown to be deficient by the FAA Airman Knowledge Test Report. I have determined [he or she] is prepared for the Instrument–[airplane, helicopter, or powered lift] practical test. FLIGHT INSTRUCTOR (OTHER THAN FLIGHT INSTRUCTORS WITH A SPORT PILOT RATING) ENDORSEMENTS",
    "category": "Additional Endorsements",
    "expires": false,
    "lines": [
      "A.40 \tPrerequisites for instrument practical tests: § 61.39(a).",
      "I certify that [First name, MI, Last name] has received and logged the required flight",
      "time/training of § 61.39(a) in preparation for the practical test within 2 calendar-months",
      "preceding the date of the test and has satisfactory knowledge of the subject areas in which",
      "[he or she] was shown to be deficient by the FAA Airman Knowledge Test Report. I have",
      "determined [he or she] is prepared for the Instrument–[airplane, helicopter, or powered",
      "lift] practical test.",
      "FLIGHT INSTRUCTOR (OTHER THAN FLIGHT INSTRUCTORS WITH A SPORT",
      "PILOT RATING) ENDORSEMENTS"
    ]
  },
  {
    "number": "A.41",
    "title": "Fundamentals of instructing knowledge test: § 61.183(d).",
    "section": {
      "id": "additional-student-pilot",
      "title": "SPORT OR RECREATIONAL PILOT CERTIFICATES"
    },
    "farReference": "§ 61.185(a)(1). I have determined that ",
    "endorsementText": "I certify that [First name, MI, Last name] has received the required fundamentals of instruction training of § 61.185(a)(1). I have determined that [he or she] is prepared for the Fundamentals of Instructing knowledge test.",
    "category": "Additional Endorsements",
    "expires": false,
    "lines": [
      "A.41 \tFundamentals of instructing knowledge test: § 61.183(d).",
      "I certify that [First name, MI, Last name] has received the required fundamentals of",
      "instruction training of § 61.185(a)(1). I have determined that [he or she] is prepared for",
      "the Fundamentals of Instructing knowledge test."
    ]
  },
  {
    "number": "A.42",
    "title": "Flight instructor aeronautical knowledge test: § 61.183(f).",
    "section": {
      "id": "additional-student-pilot",
      "title": "SPORT OR RECREATIONAL PILOT CERTIFICATES"
    },
    "farReference": "§ 61.185(a)",
    "endorsementText": "I certify that [First name, MI, Last name] has received the required training of § 61.185(a)[(2) or (3) (as appropriate to the flight instructor rating sought)]. I have determined that [he or she] is prepared for the [name of] knowledge test.",
    "category": "Additional Endorsements",
    "expires": false,
    "lines": [
      "A.42 \tFlight instructor aeronautical knowledge test: § 61.183(f).",
      "I certify that [First name, MI, Last name] has received the required training of",
      "§ 61.185(a)[(2) or (3) (as appropriate to the flight instructor rating sought)]. I have",
      "determined that [he or she] is prepared for the [name of] knowledge test."
    ]
  },
  {
    "number": "A.43",
    "title": "Flight instructor ground and flight proficiency/practical test: § 61.183(g).",
    "section": {
      "id": "additional-student-pilot",
      "title": "SPORT OR RECREATIONAL PILOT CERTIFICATES"
    },
    "farReference": "§ 61.187(b). I have determined that ",
    "endorsementText": "I certify that [First name, MI, Last name] has received the required training of § 61.187(b). I have determined that [he or she] is prepared for the CFI – [aircraft category and class] practical test. Note: The endorsement for a practical test is required in addition to the § 61.39 endorsements provided in endorsements 1 and 2 (see paragraphs A.1 and A.2). -- 8 of 18 -- 8/27/18 \tAC 61-65H Appendix A A-14",
    "category": "Additional Endorsements",
    "expires": false,
    "lines": [
      "A.43 \tFlight instructor ground and flight proficiency/practical test: § 61.183(g).",
      "I certify that [First name, MI, Last name] has received the required training of",
      "§ 61.187(b). I have determined that [he or she] is prepared for the CFI – [aircraft category",
      "and class] practical test.",
      "Note: The endorsement for a practical test is required in addition to the § 61.39",
      "endorsements provided in endorsements 1 and 2 (see paragraphs A.1 and A.2).",
      "-- 8 of 18 --",
      "8/27/18 \tAC 61-65H",
      "Appendix A",
      "A-14"
    ]
  },
  {
    "number": "A.44",
    "title": "Flight instructor certificate with instrument—(category/class) rating/practical test:",
    "section": {
      "id": "additional-student-pilot",
      "title": "SPORT OR RECREATIONAL PILOT CERTIFICATES"
    },
    "farReference": "§ 61.183(g)",
    "endorsementText": "I certify that [First name, MI, Last name] has received the required certificated flight instructor – instrument training of § 61.187(b)(7). I have determined [he or she] is prepared for the certificated flight instructor – instrument – [airplane, helicopter, or powered-lift] practical test.",
    "category": "Additional Endorsements",
    "expires": false,
    "lines": [
      "A.44 \tFlight instructor certificate with instrument—(category/class) rating/practical test:",
      "I certify that [First name, MI, Last name] has received the required certificated flight",
      "instructor – instrument training of § 61.187(b)(7). I have determined [he or she] is",
      "prepared for the certificated flight instructor – instrument – [airplane, helicopter, or",
      "powered-lift] practical test."
    ]
  },
  {
    "number": "A.45",
    "title": "Spin training: § 61.183(i)(1). The spin training endorsement is only required of flight",
    "section": {
      "id": "additional-student-pilot",
      "title": "SPORT OR RECREATIONAL PILOT CERTIFICATES"
    },
    "farReference": "§ 61.183(i)",
    "endorsementText": "I certify that [First name, MI, Last name] has received the required training of § 61.183(i) in [an airplane, a glider]. I have determined that [he or she] is competent and possesses instructional proficiency in stall awareness, spin entry, spins, and spin recovery procedures.",
    "category": "Additional Endorsements",
    "expires": false,
    "lines": [
      "A.45 \tSpin training: § 61.183(i)(1). The spin training endorsement is only required of flight",
      "I certify that [First name, MI, Last name] has received the required training of § 61.183(i)",
      "in [an airplane, a glider]. I have determined that [he or she] is competent and possesses",
      "instructional proficiency in stall awareness, spin entry, spins, and spin recovery",
      "procedures."
    ]
  },
  {
    "number": "A.46",
    "title": "Helicopter Touchdown Autorotation: FAA-S-8081-7, Flight Instructor Practical",
    "section": {
      "id": "additional-student-pilot",
      "title": "SPORT OR RECREATIONAL PILOT CERTIFICATES"
    },
    "farReference": null,
    "endorsementText": "I certify that [First name, MI, Last name] has received training in straight-in and 180-degree autorotations to include touchdown. I have determined that [he or she] is competent in instructional knowledge relating to the elements, common errors, performance, and correction of common errors related to straight-in and 180-degree autorotations.",
    "category": "Additional Endorsements",
    "expires": false,
    "lines": [
      "A.46 \tHelicopter Touchdown Autorotation: FAA-S-8081-7, Flight Instructor Practical",
      "I certify that [First name, MI, Last name] has received training in straight-in and",
      "180-degree autorotations to include touchdown. I have determined that [he or she] is",
      "competent in instructional knowledge relating to the elements, common errors,",
      "performance, and correction of common errors related to straight-in and 180-degree",
      "autorotations."
    ]
  },
  {
    "number": "A.47",
    "title": "Fundamentals of instructing knowledge test: § 61.405(a)(1).",
    "section": {
      "id": "additional-student-pilot",
      "title": "SPORT OR RECREATIONAL PILOT CERTIFICATES"
    },
    "farReference": "§ 61.405(a)(1). I have determined that ",
    "endorsementText": "I certify that [First name, MI, Last name] has received the required training in accordance with § 61.405(a)(1). I have determined that [he or she] is prepared for the Fundamentals of Instructing Knowledge Test.",
    "category": "Additional Endorsements",
    "expires": false,
    "lines": [
      "A.47 \tFundamentals of instructing knowledge test: § 61.405(a)(1).",
      "I certify that [First name, MI, Last name] has received the required training in accordance",
      "with § 61.405(a)(1). I have determined that [he or she] is prepared for the Fundamentals",
      "of Instructing Knowledge Test."
    ]
  },
  {
    "number": "A.48",
    "title": "Sport pilot flight instructor aeronautical knowledge test: §§ 61.35(a)(1) and",
    "section": {
      "id": "additional-student-pilot",
      "title": "SPORT OR RECREATIONAL PILOT CERTIFICATES"
    },
    "farReference": "§ 61.405(a)(2). I have determined that ",
    "endorsementText": "I certify that [First name, MI, Last name] has received the required training of § 61.405(a)(2). I have determined that [he or she] is prepared for the [name of the knowledge test]. -- 9 of 18 -- 8/27/18 \tAC 61-65H Appendix A A-15",
    "category": "Additional Endorsements",
    "expires": false,
    "lines": [
      "A.48 \tSport pilot flight instructor aeronautical knowledge test: §§ 61.35(a)(1) and",
      "I certify that [First name, MI, Last name] has received the required training of",
      "§ 61.405(a)(2). I have determined that [he or she] is prepared for the [name of the",
      "knowledge test].",
      "-- 9 of 18 --",
      "8/27/18 \tAC 61-65H",
      "Appendix A",
      "A-15"
    ]
  },
  {
    "number": "A.49",
    "title": "Flight instructor flight proficiency check to provide training if a different category",
    "section": {
      "id": "additional-student-pilot",
      "title": "SPORT OR RECREATIONAL PILOT CERTIFICATES"
    },
    "farReference": "§ 61.409 and 61.419.",
    "endorsementText": "I certify that [First name, MI, Last name] has received the required training in accordance with §§ 61.409 and 61.419 and have determined that [he or she] is prepared for a proficiency check for the flight instructor with a sport pilot rating in a [aircraft category and class].",
    "category": "Additional Endorsements",
    "expires": false,
    "lines": [
      "A.49 \tFlight instructor flight proficiency check to provide training if a different category",
      "I certify that [First name, MI, Last name] has received the required training in accordance",
      "with §§ 61.409 and 61.419 and have determined that [he or she] is prepared for a",
      "proficiency check for the flight instructor with a sport pilot rating in a [aircraft category",
      "and class]."
    ]
  },
  {
    "number": "A.50",
    "title": "Passing the flight instructor flight proficiency check to provide training in a",
    "section": {
      "id": "additional-student-pilot",
      "title": "SPORT OR RECREATIONAL PILOT CERTIFICATES"
    },
    "farReference": "§ 61.409",
    "endorsementText": "I certify that [First name, MI, Last name] has met the requirements in accordance with §§ 61.409 and 61.419. I have determined that [he or she] is proficient and authorized for the additional [aircraft category and class] flight instructor privilege.",
    "category": "Additional Endorsements",
    "expires": false,
    "lines": [
      "A.50 \tPassing the flight instructor flight proficiency check to provide training in a",
      "I certify that [First name, MI, Last name] has met the requirements in accordance with",
      "§§ 61.409 and 61.419. I have determined that [he or she] is proficient and authorized for",
      "the additional [aircraft category and class] flight instructor privilege."
    ]
  },
  {
    "number": "A.51",
    "title": "Flight instructor practical test: §§ 61.409 and 61.411. This endorsement is required in",
    "section": {
      "id": "additional-student-pilot",
      "title": "SPORT OR RECREATIONAL PILOT CERTIFICATES"
    },
    "farReference": "§ 61.39 endorsements provided in paragraphs A.1 and A.2.",
    "endorsementText": "I certify that [First name, MI, Last name] has received the required training of § 61.409 and met the aeronautical experience requirements of § 61.411. I have determined that [he or she] is prepared for the flight instructor with a sport pilot rating practical test in a [aircraft category and class]. /s/ [date] S. P. Examiner 987654321 Exp. 12-31-19",
    "category": "Additional Endorsements",
    "expires": false,
    "lines": [
      "A.51 \tFlight instructor practical test: §§ 61.409 and 61.411. This endorsement is required in",
      "I certify that [First name, MI, Last name] has received the required training of § 61.409",
      "and met the aeronautical experience requirements of § 61.411. I have determined that [he",
      "or she] is prepared for the flight instructor with a sport pilot rating practical test in a",
      "[aircraft category and class].",
      "/s/ [date] S. P. Examiner 987654321 Exp. 12-31-19"
    ]
  },
  {
    "number": "A.52",
    "title": "Passing the flight instructor practical test: §§ 61.409 and 61.411. This endorsement is",
    "section": {
      "id": "additional-student-pilot",
      "title": "SPORT OR RECREATIONAL PILOT CERTIFICATES"
    },
    "farReference": "§ 61.417 and is issued by a Designated Pilot Examiner (DPE).",
    "endorsementText": "I certify that [First name, MI, Last name] has met the requirements in accordance with §§ 61.409 and 61.411. I have determined that [he or she] is proficient and authorized for the [aircraft category and class] flight instructor privilege. /s/ [date] S. P. Examiner 987654321 Exp. 12-31-19",
    "category": "Additional Endorsements",
    "expires": false,
    "lines": [
      "A.52 \tPassing the flight instructor practical test: §§ 61.409 and 61.411. This endorsement is",
      "I certify that [First name, MI, Last name] has met the requirements in accordance with",
      "§§ 61.409 and 61.411. I have determined that [he or she] is proficient and authorized for",
      "the [aircraft category and class] flight instructor privilege.",
      "/s/ [date] S. P. Examiner 987654321 Exp. 12-31-19"
    ]
  },
  {
    "number": "A.53",
    "title": "Sport pilot instructor to train sport pilots on flight by reference to instruments:",
    "section": {
      "id": "additional-student-pilot",
      "title": "SPORT OR RECREATIONAL PILOT CERTIFICATES"
    },
    "farReference": "§ 61.412. This endorsement from an instructor certificated under part 61 subpart H to a",
    "endorsementText": "I certify that I have given [First name, MI, Last name] 3 hours of flight training and 1 hour of ground instruction specific to providing flight training on control and maneuvering an airplane solely by reference to the instruments in accordance with § 61.412. I have determined that [he or she] is proficient and authorized to provide training on control and maneuvering an airplane solely by reference to the flight instruments to this instructor’s sport pilot candidate, who intends to operate an LSA airplane with a V H greater than 87 KCAS on a cross-country flight. /s/ [date] Subpart H Instructor 987654321 Exp. 12-31-19 -- 10 of 18 -- 8/27/18 \tAC 61-65H Appendix A A-16",
    "category": "Additional Endorsements",
    "expires": false,
    "lines": [
      "A.53 \tSport pilot instructor to train sport pilots on flight by reference to instruments:",
      "I certify that I have given [First name, MI, Last name] 3 hours of flight training and",
      "1 hour of ground instruction specific to providing flight training on control and",
      "maneuvering an airplane solely by reference to the instruments in accordance with",
      "§ 61.412. I have determined that [he or she] is proficient and authorized to provide",
      "training on control and maneuvering an airplane solely by reference to the flight",
      "instruments to this instructor’s sport pilot candidate, who intends to operate an LSA",
      "airplane with a V H greater than 87 KCAS on a cross-country flight.",
      "/s/ [date] Subpart H Instructor 987654321 Exp. 12-31-19",
      "-- 10 of 18 --",
      "8/27/18 \tAC 61-65H",
      "Appendix A",
      "A-16"
    ]
  },
  {
    "number": "A.54",
    "title": "Spin training: § 61.405(b)(1)(ii). This spin training endorsement is only required for",
    "section": {
      "id": "additional-student-pilot",
      "title": "SPORT OR RECREATIONAL PILOT CERTIFICATES"
    },
    "farReference": "§ 61.405(b)(1)(ii). I have determined that ",
    "endorsementText": "I certify that [First name, MI, Last name] has received the required training of § 61.405(b)(1)(ii). I have determined that [he or she] is competent and possesses instructional proficiency in stall awareness, spin entry, spins, and spin recovery procedures.",
    "category": "Additional Endorsements",
    "expires": false,
    "lines": [
      "A.54 \tSpin training: § 61.405(b)(1)(ii). This spin training endorsement is only required for",
      "I certify that [First name, MI, Last name] has received the required training of",
      "§ 61.405(b)(1)(ii). I have determined that [he or she] is competent and possesses",
      "instructional proficiency in stall awareness, spin entry, spins, and spin recovery",
      "procedures."
    ]
  },
  {
    "number": "A.55",
    "title": "Ground instructor who does not meet the recent experience requirements:",
    "section": {
      "id": "additional-student-pilot",
      "title": "SPORT OR RECREATIONAL PILOT CERTIFICATES"
    },
    "farReference": "§ 61.217(d). This endorsement is issued by an authorized instructor (ground or flight) as",
    "endorsementText": "I certify that [First name, MI, Last name] has demonstrated knowledge in the subject areas prescribed for a (basic, advanced, instrument) ground instructor under § 61.213(a)(3) and (a)(4), as appropriate. SPECIAL FEDERAL AVIATION REGULATION (SFAR) 73, ROBINSON R-22/R-44 SPECIAL TRAINING AND EXPERIENCE REQUIREMENTS, ENDORSEMENTS",
    "category": "Additional Endorsements",
    "expires": false,
    "lines": [
      "A.55 \tGround instructor who does not meet the recent experience requirements:",
      "I certify that [First name, MI, Last name] has demonstrated knowledge in the subject",
      "areas prescribed for a (basic, advanced, instrument) ground instructor under",
      "§ 61.213(a)(3) and (a)(4), as appropriate.",
      "SPECIAL FEDERAL AVIATION REGULATION (SFAR) 73, ROBINSON R-22/R-44",
      "SPECIAL TRAINING AND EXPERIENCE REQUIREMENTS, ENDORSEMENTS"
    ]
  },
  {
    "number": "A.56",
    "title": "R-22/R-44 awareness training: SFAR 73, section 2(a)(1) or (2).",
    "section": {
      "id": "additional-student-pilot",
      "title": "SPORT OR RECREATIONAL PILOT CERTIFICATES"
    },
    "farReference": null,
    "endorsementText": "I certify that [First name, MI, Last name, Pilot Certificate No. _____] has received the Awareness Training required by SFAR 73, section 2(a)(3)(i–v).",
    "category": "Additional Endorsements",
    "expires": false,
    "lines": [
      "A.56 \tR-22/R-44 awareness training: SFAR 73, section 2(a)(1) or (2).",
      "I certify that [First name, MI, Last name, Pilot Certificate No. _____] has received the",
      "Awareness Training required by SFAR 73, section 2(a)(3)(i–v)."
    ]
  },
  {
    "number": "A.57",
    "title": "R-22 solo endorsement: SFAR 73, section 2(b)(3).",
    "section": {
      "id": "additional-student-pilot",
      "title": "SPORT OR RECREATIONAL PILOT CERTIFICATES"
    },
    "farReference": null,
    "endorsementText": "I certify that [First name, MI, Last name, Pilot Certificate No. _____] meets the experience requirements of SFAR 73, section 2(b)(3) and has been given training specified by SFAR 73, section 2(b)(3)(i–iv). [He or She] has been found proficient to solo the R-22 helicopter.",
    "category": "Additional Endorsements",
    "expires": false,
    "lines": [
      "A.57 \tR-22 solo endorsement: SFAR 73, section 2(b)(3).",
      "I certify that [First name, MI, Last name, Pilot Certificate No. _____] meets the",
      "experience requirements of SFAR 73, section 2(b)(3) and has been given training",
      "specified by SFAR 73, section 2(b)(3)(i–iv). [He or She] has been found proficient to",
      "solo the R-22 helicopter."
    ]
  },
  {
    "number": "A.58",
    "title": "R-22 pilot-in-command endorsement: SFAR 73, section 2(b)(1)(ii).",
    "section": {
      "id": "additional-student-pilot",
      "title": "SPORT OR RECREATIONAL PILOT CERTIFICATES"
    },
    "farReference": null,
    "endorsementText": "I certify that [First name, MI, Last name, Pilot Certificate No. _____] has been given training specified by SFAR 73, section 2(b)(1)(ii)(A–D) for Robinson R-22 helicopters and is proficient to act as pilot in command. An annual flight review must be completed by [date 12 calendar-months after date of this endorsement] unless the requirements of SFAR 73, section 2(b)(1)(i) are met. -- 11 of 18 -- 8/27/18 \tAC 61-65H Appendix A A-17",
    "category": "Additional Endorsements",
    "expires": false,
    "lines": [
      "A.58 \tR-22 pilot-in-command endorsement: SFAR 73, section 2(b)(1)(ii).",
      "I certify that [First name, MI, Last name, Pilot Certificate No. _____] has been given",
      "training specified by SFAR 73, section 2(b)(1)(ii)(A–D) for Robinson R-22 helicopters",
      "and is proficient to act as pilot in command. An annual flight review must be completed",
      "by [date 12 calendar-months after date of this endorsement] unless the requirements of",
      "SFAR 73, section 2(b)(1)(i) are met.",
      "-- 11 of 18 --",
      "8/27/18 \tAC 61-65H",
      "Appendix A",
      "A-17"
    ]
  },
  {
    "number": "A.59",
    "title": "R-22 flight instructor endorsement: SFAR 73, section 2(b)(5)(iv). This endorsement",
    "section": {
      "id": "additional-student-pilot",
      "title": "SPORT OR RECREATIONAL PILOT CERTIFICATES"
    },
    "farReference": null,
    "endorsementText": "I certify that [First name, MI, Last name], holder of CFI Certificate No. [_____], meets the experience requirements, and has completed the flight training specified by SFAR 73, section 2(b)(5)(i–ii) and (iii)(A–D), and has demonstrated an ability to provide instruction on the general subject areas of SFAR 73, section 2(a)(3) and the flight training identified in SFAR 73, section 2(b)(5)(iii) in a Robinson R-22 helicopter. /s/ [date] J. J. Jones DPE Designation Number, Exp. 12-31-19; or /s/ [date] I. M. Inspector FAA Aviation Safety Inspector",
    "category": "Additional Endorsements",
    "expires": false,
    "lines": [
      "A.59 \tR-22 flight instructor endorsement: SFAR 73, section 2(b)(5)(iv). This endorsement",
      "I certify that [First name, MI, Last name], holder of CFI Certificate No. [_____], meets",
      "the experience requirements, and has completed the flight training specified by SFAR 73,",
      "section 2(b)(5)(i–ii) and (iii)(A–D), and has demonstrated an ability to provide instruction",
      "on the general subject areas of SFAR 73, section 2(a)(3) and the flight training identified",
      "in SFAR 73, section 2(b)(5)(iii) in a Robinson R-22 helicopter.",
      "/s/ [date] J. J. Jones DPE Designation Number, Exp. 12-31-19; or",
      "/s/ [date] I. M. Inspector FAA Aviation Safety Inspector"
    ]
  },
  {
    "number": "A.60",
    "title": "Flight review in an R-22 helicopter: SFAR 73, section 2(c)(1) and (3).",
    "section": {
      "id": "additional-student-pilot",
      "title": "SPORT OR RECREATIONAL PILOT CERTIFICATES"
    },
    "farReference": "§ 61.56 and SFAR 73",
    "endorsementText": "I certify that [First name, MI, Last name, Pilot Certificate No. _____] has satisfactorily completed the flight review in an R-22 required by § 61.56 and SFAR 73, section 2(c)(1) and (3), on [date of flight review].",
    "category": "Additional Endorsements",
    "expires": false,
    "lines": [
      "A.60 \tFlight review in an R-22 helicopter: SFAR 73, section 2(c)(1) and (3).",
      "I certify that [First name, MI, Last name, Pilot Certificate No. _____] has satisfactorily",
      "completed the flight review in an R-22 required by § 61.56 and SFAR 73, section 2(c)(1)",
      "and (3), on [date of flight review]."
    ]
  },
  {
    "number": "A.61",
    "title": "R-44 solo endorsement: SFAR 73, section 2(b)(4).",
    "section": {
      "id": "additional-student-pilot",
      "title": "SPORT OR RECREATIONAL PILOT CERTIFICATES"
    },
    "farReference": null,
    "endorsementText": "I certify that [First name, MI, Last name, Pilot Certificate No. _____] meets the experience requirements of SFAR 73, section 2(b)(4) and has been given training specified by SFAR 73, section 2(b)(4)(i–iv). [He or She] has been found proficient to solo the R-44 helicopter.",
    "category": "Additional Endorsements",
    "expires": false,
    "lines": [
      "A.61 \tR-44 solo endorsement: SFAR 73, section 2(b)(4).",
      "I certify that [First name, MI, Last name, Pilot Certificate No. _____] meets the",
      "experience requirements of SFAR 73, section 2(b)(4) and has been given training",
      "specified by SFAR 73, section 2(b)(4)(i–iv). [He or She] has been found proficient to",
      "solo the R-44 helicopter."
    ]
  },
  {
    "number": "A.62",
    "title": "R-44 pilot-in-command endorsement: SFAR 73, section 2(b)(2)(ii).",
    "section": {
      "id": "additional-student-pilot",
      "title": "SPORT OR RECREATIONAL PILOT CERTIFICATES"
    },
    "farReference": null,
    "endorsementText": "I certify that [First name, MI, Last name, Pilot Certificate No. _____] has been given training specified by SFAR 73, section 2(b)(2)(ii)(A–D) for Robinson R-44 helicopters and is proficient to act as pilot in command. An annual flight review must be completed by [date 12 calendar-months after date of this endorsement] unless the requirements of SFAR 73, section 2(b)(2)(i) are met.",
    "category": "Additional Endorsements",
    "expires": false,
    "lines": [
      "A.62 \tR-44 pilot-in-command endorsement: SFAR 73, section 2(b)(2)(ii).",
      "I certify that [First name, MI, Last name, Pilot Certificate No. _____] has been given",
      "training specified by SFAR 73, section 2(b)(2)(ii)(A–D) for Robinson R-44 helicopters",
      "and is proficient to act as pilot in command. An annual flight review must be completed",
      "by [date 12 calendar-months after date of this endorsement] unless the requirements of",
      "SFAR 73, section 2(b)(2)(i) are met."
    ]
  },
  {
    "number": "A.63",
    "title": "R-44 flight instructor endorsement: SFAR 73, section 2(b)(5)(iv). This endorsement",
    "section": {
      "id": "additional-student-pilot",
      "title": "SPORT OR RECREATIONAL PILOT CERTIFICATES"
    },
    "farReference": null,
    "endorsementText": "I certify that [First name, MI, Last name], holder of CFI Certificate No. [_____], meets the experience requirements and has completed the flight training specified by SFAR 73, section 2(b)(5)(i–ii) and (iii)(A–D), and has demonstrated an ability to provide instruction on the general subject areas of SFAR 73, section 2(a)(3) and the flight training identified in SFAR 73, section 2(b)(5)(iii) in a Robinson R-44 helicopter. /s/ [date] J. J. Jones DPE Designation Number, Exp. 12-31-19; or /s/ [date] I. M. Inspector FAA Aviation Safety Inspector -- 12 of 18 -- 8/27/18 \tAC 61-65H Appendix A A-18",
    "category": "Additional Endorsements",
    "expires": false,
    "lines": [
      "A.63 \tR-44 flight instructor endorsement: SFAR 73, section 2(b)(5)(iv). This endorsement",
      "I certify that [First name, MI, Last name], holder of CFI Certificate No. [_____], meets",
      "the experience requirements and has completed the flight training specified by SFAR 73,",
      "section 2(b)(5)(i–ii) and (iii)(A–D), and has demonstrated an ability to provide instruction",
      "on the general subject areas of SFAR 73, section 2(a)(3) and the flight training identified",
      "in SFAR 73, section 2(b)(5)(iii) in a Robinson R-44 helicopter.",
      "/s/ [date] J. J. Jones DPE Designation Number, Exp. 12-31-19; or",
      "/s/ [date] I. M. Inspector FAA Aviation Safety Inspector",
      "-- 12 of 18 --",
      "8/27/18 \tAC 61-65H",
      "Appendix A",
      "A-18"
    ]
  },
  {
    "number": "A.64",
    "title": "Flight review in an R-44 helicopter: SFAR 73, section 2(c)(2) and (3).",
    "section": {
      "id": "additional-student-pilot",
      "title": "SPORT OR RECREATIONAL PILOT CERTIFICATES"
    },
    "farReference": "§ 61.56 and SFAR 73",
    "endorsementText": "I certify that [First name, MI, Last name, Pilot Certificate No. _____] has satisfactorily completed the flight review in an R-44 required by 14 CFR, § 61.56 and SFAR 73, section 2(c)(2) and (3), on [date of flight review].",
    "category": "Additional Endorsements",
    "expires": false,
    "lines": [
      "A.64 \tFlight review in an R-44 helicopter: SFAR 73, section 2(c)(2) and (3).",
      "I certify that [First name, MI, Last name, Pilot Certificate No. _____] has satisfactorily",
      "completed the flight review in an R-44 required by 14 CFR, § 61.56 and SFAR 73,",
      "section 2(c)(2) and (3), on [date of flight review]."
    ]
  },
  {
    "number": "A.65",
    "title": "Completion of a flight review: § 61.56(a) and (c). No logbook entry reflecting",
    "section": {
      "id": "additional-student-pilot",
      "title": "SPORT OR RECREATIONAL PILOT CERTIFICATES"
    },
    "farReference": "§ 61.56(a) on ",
    "endorsementText": "I certify that [First name, MI, Last name], [grade of pilot certificate], [certificate number], has satisfactorily completed a flight review of § 61.56(a) on [date].",
    "category": "Additional Endorsements",
    "expires": false,
    "lines": [
      "A.65 \tCompletion of a flight review: § 61.56(a) and (c). No logbook entry reflecting",
      "I certify that [First name, MI, Last name], [grade of pilot certificate], [certificate number],",
      "has satisfactorily completed a flight review of § 61.56(a) on [date]."
    ]
  },
  {
    "number": "A.66",
    "title": "Completion of any phase of an FAA-sponsored Pilot Proficiency Program",
    "section": {
      "id": "additional-student-pilot",
      "title": "SPORT OR RECREATIONAL PILOT CERTIFICATES"
    },
    "farReference": "§ 61.56(e).",
    "endorsementText": "I certify that [First name, MI, Last name], [grade of pilot certificate], [certificate number], has satisfactorily completed Level: [Basic/Advanced/Master, as appropriate], PHASE NO. [..] OF A WINGS PROGRAM ON [DATE].",
    "category": "Additional Endorsements",
    "expires": false,
    "lines": [
      "A.66 \tCompletion of any phase of an FAA-sponsored Pilot Proficiency Program",
      "I certify that [First name, MI, Last name], [grade of pilot certificate], [certificate number],",
      "has satisfactorily completed Level: [Basic/Advanced/Master, as appropriate],",
      "PHASE NO. [..] OF A WINGS PROGRAM ON [DATE]."
    ]
  },
  {
    "number": "A.67",
    "title": "Completion of an instrument proficiency check: § 61.57(d). No logbook entry",
    "section": {
      "id": "additional-student-pilot",
      "title": "SPORT OR RECREATIONAL PILOT CERTIFICATES"
    },
    "farReference": "§ 61.57(d) in a ",
    "endorsementText": "I certify that [First name, MI, Last name], [grade of pilot certificate], [certificate number], has satisfactorily completed the instrument proficiency check of § 61.57(d) in a [make and model] aircraft on [date].",
    "category": "Additional Endorsements",
    "expires": false,
    "lines": [
      "A.67 \tCompletion of an instrument proficiency check: § 61.57(d). No logbook entry",
      "I certify that [First name, MI, Last name], [grade of pilot certificate], [certificate number],",
      "has satisfactorily completed the instrument proficiency check of § 61.57(d) in a [make",
      "and model] aircraft on [date]."
    ]
  },
  {
    "number": "A.68",
    "title": "To act as pilot in command in a complex airplane: § 61.31(e).",
    "section": {
      "id": "additional-student-pilot",
      "title": "SPORT OR RECREATIONAL PILOT CERTIFICATES"
    },
    "farReference": "§ 61.31(e) in a ",
    "endorsementText": "I certify that [First name, MI, Last name], [grade of pilot certificate], [certificate number], has received the required training of § 61.31(e) in a [make and model] complex airplane. I have determined that [he or she] is proficient in the operation and systems of a complex airplane.",
    "category": "Additional Endorsements",
    "expires": false,
    "lines": [
      "A.68 \tTo act as pilot in command in a complex airplane: § 61.31(e).",
      "I certify that [First name, MI, Last name], [grade of pilot certificate], [certificate number],",
      "has received the required training of § 61.31(e) in a [make and model] complex airplane.",
      "I have determined that [he or she] is proficient in the operation and systems of a complex",
      "airplane."
    ]
  },
  {
    "number": "A.69",
    "title": "To act as pilot in command in a high-performance airplane: § 61.31(f).",
    "section": {
      "id": "additional-student-pilot",
      "title": "SPORT OR RECREATIONAL PILOT CERTIFICATES"
    },
    "farReference": "§ 61.31(f) in a ",
    "endorsementText": "I certify that [First name, MI, Last name], [grade of pilot certificate], [certificate number], has received the required training of § 61.31(f) in a [make and model] high performance airplane. I have determined that [he or she] is proficient in the operation and systems of a high-performance airplane. -- 13 of 18 -- 8/27/18 \tAC 61-65H Appendix A A-19",
    "category": "Additional Endorsements",
    "expires": false,
    "lines": [
      "A.69 \tTo act as pilot in command in a high-performance airplane: § 61.31(f).",
      "I certify that [First name, MI, Last name], [grade of pilot certificate], [certificate number],",
      "has received the required training of § 61.31(f) in a [make and model] high performance",
      "airplane. I have determined that [he or she] is proficient in the operation and systems of a",
      "high-performance airplane.",
      "-- 13 of 18 --",
      "8/27/18 \tAC 61-65H",
      "Appendix A",
      "A-19"
    ]
  },
  {
    "number": "A.70",
    "title": "To act as pilot in command in a pressurized aircraft capable of high-altitude",
    "section": {
      "id": "additional-student-pilot",
      "title": "SPORT OR RECREATIONAL PILOT CERTIFICATES"
    },
    "farReference": "§ 61.31(g).",
    "endorsementText": "I certify that [First name, MI, Last name], [grade of pilot certificate], [certificate number], has received the required training of § 61.31(g) in a [make and model] pressurized aircraft. I have determined that [he or she] is proficient in the operation and systems of a pressurized aircraft.",
    "category": "Additional Endorsements",
    "expires": false,
    "lines": [
      "A.70 \tTo act as pilot in command in a pressurized aircraft capable of high-altitude",
      "I certify that [First name, MI, Last name], [grade of pilot certificate], [certificate number],",
      "has received the required training of § 61.31(g) in a [make and model] pressurized",
      "aircraft. I have determined that [he or she] is proficient in the operation and systems of a",
      "pressurized aircraft."
    ]
  },
  {
    "number": "A.71",
    "title": "To act as pilot in command in a tailwheel airplane: § 61.31(i). This endorsement may",
    "section": {
      "id": "additional-student-pilot",
      "title": "SPORT OR RECREATIONAL PILOT CERTIFICATES"
    },
    "farReference": "§ 61.31(i) in a ",
    "endorsementText": "I certify that [First name, MI, Last name], [grade of pilot certificate], [certificate number], has received the required training of § 61.31(i) in a [make and model] of tailwheel airplane. I have determined that [he or she] is proficient in the operation of a tailwheel airplane.",
    "category": "Additional Endorsements",
    "expires": false,
    "lines": [
      "A.71 \tTo act as pilot in command in a tailwheel airplane: § 61.31(i). This endorsement may",
      "I certify that [First name, MI, Last name], [grade of pilot certificate], [certificate number],",
      "has received the required training of § 61.31(i) in a [make and model] of tailwheel",
      "airplane. I have determined that [he or she] is proficient in the operation of a tailwheel",
      "airplane."
    ]
  },
  {
    "number": "A.72",
    "title": "To act as pilot in command of an aircraft in solo operations when the pilot does not",
    "section": {
      "id": "additional-student-pilot",
      "title": "SPORT OR RECREATIONAL PILOT CERTIFICATES"
    },
    "farReference": "§ 61.31(d)(2).",
    "endorsementText": "I certify that [First name, MI, Last name] has received the training as required by § 61.31(d)(2) to serve as a pilot in command in a [specific category and class] of aircraft. I have determined that [he or she] is prepared to solo that [make and model] aircraft. Limitations: [optional].",
    "category": "Additional Endorsements",
    "expires": false,
    "lines": [
      "A.72 \tTo act as pilot in command of an aircraft in solo operations when the pilot does not",
      "I certify that [First name, MI, Last name] has received the training as required by",
      "§ 61.31(d)(2) to serve as a pilot in command in a [specific category and class] of aircraft.",
      "I have determined that [he or she] is prepared to solo that [make and model] aircraft.",
      "Limitations: [optional]."
    ]
  },
  {
    "number": "A.73",
    "title": "Retesting after failure of a knowledge or practical test: § 61.49. In the case of a failed",
    "section": {
      "id": "additional-student-pilot",
      "title": "SPORT OR RECREATIONAL PILOT CERTIFICATES"
    },
    "farReference": "§ 61.49. I have determined that ",
    "endorsementText": "I certify that [First name, MI, Last name] has received the additional [flight and/or ground, as appropriate] training as required by § 61.49. I have determined that [he or she] is proficient to pass the [name of] knowledge/practical test.",
    "category": "Additional Endorsements",
    "expires": false,
    "lines": [
      "A.73 \tRetesting after failure of a knowledge or practical test: § 61.49. In the case of a failed",
      "I certify that [First name, MI, Last name] has received the additional [flight and/or",
      "ground, as appropriate] training as required by § 61.49. I have determined that [he or she]",
      "is proficient to pass the [name of] knowledge/practical test."
    ]
  },
  {
    "number": "A.74",
    "title": "Additional aircraft category or class rating (other than ATP): § 61.63(b) or (c).",
    "section": {
      "id": "additional-student-pilot",
      "title": "SPORT OR RECREATIONAL PILOT CERTIFICATES"
    },
    "farReference": null,
    "endorsementText": "I certify that [First name, MI, Last name], [grade of pilot certificate], [certificate number], has received the required training for an additional [aircraft category/class rating]. I have determined that [he or she] is prepared for the [name of] practical test for the addition of a [name of] [specific aircraft category/class/type] type rating.",
    "category": "Additional Endorsements",
    "expires": false,
    "lines": [
      "A.74 \tAdditional aircraft category or class rating (other than ATP): § 61.63(b) or (c).",
      "I certify that [First name, MI, Last name], [grade of pilot certificate], [certificate number],",
      "has received the required training for an additional [aircraft category/class rating]. I have",
      "determined that [he or she] is prepared for the [name of] practical test for the addition of",
      "a [name of] [specific aircraft category/class/type] type rating."
    ]
  },
  {
    "number": "A.75",
    "title": "Type rating only, already holds the appropriate category or class rating (other than",
    "section": {
      "id": "additional-student-pilot",
      "title": "SPORT OR RECREATIONAL PILOT CERTIFICATES"
    },
    "farReference": "§ 61.63(d)(2).",
    "endorsementText": "I certify that [First name, MI, Last name] has received the required training of § 61.63(d)(2) for an addition of a [name of] type rating. -- 14 of 18 -- 8/27/18 \tAC 61-65H Appendix A A-20",
    "category": "Additional Endorsements",
    "expires": false,
    "lines": [
      "A.75 \tType rating only, already holds the appropriate category or class rating (other than",
      "I certify that [First name, MI, Last name] has received the required training of",
      "§ 61.63(d)(2) for an addition of a [name of] type rating.",
      "-- 14 of 18 --",
      "8/27/18 \tAC 61-65H",
      "Appendix A",
      "A-20"
    ]
  },
  {
    "number": "A.76",
    "title": "Type rating concurrently with an additional category or class rating (other than",
    "section": {
      "id": "additional-student-pilot",
      "title": "SPORT OR RECREATIONAL PILOT CERTIFICATES"
    },
    "farReference": "§ 61.63(d)(2).",
    "endorsementText": "I certify that [First name, MI, Last name] has received the required training of § 61.63(d)(2) for an addition of a [name of] [specific category/class/type] type rating. I have determined that [he or she] is prepared for the [name of] practical test for the addition of a [name of] [specific aircraft category/class/type] type rating.",
    "category": "Additional Endorsements",
    "expires": false,
    "lines": [
      "A.76 \tType rating concurrently with an additional category or class rating (other than",
      "I certify that [First name, MI, Last name] has received the required training of",
      "§ 61.63(d)(2) for an addition of a [name of] [specific category/class/type] type rating.",
      "I have determined that [he or she] is prepared for the [name of] practical test for the",
      "addition of a [name of] [specific aircraft category/class/type] type rating."
    ]
  },
  {
    "number": "A.77",
    "title": "Type rating only, already holds the appropriate category or class rating (at the",
    "section": {
      "id": "additional-student-pilot",
      "title": "SPORT OR RECREATIONAL PILOT CERTIFICATES"
    },
    "farReference": "§ 61.157(b)(2).",
    "endorsementText": "I certify that [First name, MI, Last name] has received the required training of § 61.157(b)(2) for an addition of a [name of] type rating.",
    "category": "Additional Endorsements",
    "expires": false,
    "lines": [
      "A.77 \tType rating only, already holds the appropriate category or class rating (at the",
      "I certify that [First name, MI, Last name] has received the required training of",
      "§ 61.157(b)(2) for an addition of a [name of] type rating."
    ]
  },
  {
    "number": "A.78",
    "title": "Type rating concurrently with an additional category or class rating (at the",
    "section": {
      "id": "additional-student-pilot",
      "title": "SPORT OR RECREATIONAL PILOT CERTIFICATES"
    },
    "farReference": "§ 61.157(b)(2).",
    "endorsementText": "I certify that [First name, MI, Last name] has received the required training of § 61.157(b)(2) for an addition of a [name of the specific category/class/type] type rating.",
    "category": "Additional Endorsements",
    "expires": false,
    "lines": [
      "A.78 \tType rating concurrently with an additional category or class rating (at the",
      "I certify that [First name, MI, Last name] has received the required training of",
      "§ 61.157(b)(2) for an addition of a [name of the specific category/class/type] type rating."
    ]
  },
  {
    "number": "A.79",
    "title": "Launch procedures for operating a glider: § 61.31(j).",
    "section": {
      "id": "additional-student-pilot",
      "title": "SPORT OR RECREATIONAL PILOT CERTIFICATES"
    },
    "farReference": null,
    "endorsementText": "I certify that [First name, MI, Last name], [grade of pilot certificate], [certificate number], has received the required training in a glider [make and model] for [ground-tow, aerotow, self-launch] procedure. I have determined that [he or she] is proficient in [ground-tow, aerotow, self-launch] procedure.",
    "category": "Additional Endorsements",
    "expires": false,
    "lines": [
      "A.79 \tLaunch procedures for operating a glider: § 61.31(j).",
      "I certify that [First name, MI, Last name], [grade of pilot certificate], [certificate number],",
      "has received the required training in a glider [make and model] for [ground-tow, aerotow,",
      "self-launch] procedure. I have determined that [he or she] is proficient in [ground-tow,",
      "aerotow, self-launch] procedure."
    ]
  },
  {
    "number": "A.80",
    "title": "Glider and unpowered ultralight vehicle towing experience: § 61.69(a)(5). This",
    "section": {
      "id": "additional-student-pilot",
      "title": "SPORT OR RECREATIONAL PILOT CERTIFICATES"
    },
    "farReference": "§ 61.69(c) and (d) and who",
    "endorsementText": "I certify that [First name, MI, Last name], [grade of pilot certificate], [certificate number], has accomplished at least three flights in an aircraft while towing [a glider or unpowered ultralight vehicle, or while simulating towing flight procedures, as applicable]. /s/ [date] J. J. Jones 987654321",
    "category": "Additional Endorsements",
    "expires": false,
    "lines": [
      "A.80 \tGlider and unpowered ultralight vehicle towing experience: § 61.69(a)(5). This",
      "I certify that [First name, MI, Last name], [grade of pilot certificate], [certificate number],",
      "has accomplished at least three flights in an aircraft while towing [a glider or unpowered",
      "ultralight vehicle, or while simulating towing flight procedures, as applicable].",
      "/s/ [date] J. J. Jones 987654321"
    ]
  },
  {
    "number": "A.81",
    "title": "Glider and unpowered ultralight vehicle towing ground and flight: § 61.69(a)(3).",
    "section": {
      "id": "additional-student-pilot",
      "title": "SPORT OR RECREATIONAL PILOT CERTIFICATES"
    },
    "farReference": null,
    "endorsementText": "I certify that [First name, MI, Last name], [grade of pilot certificate], [certificate number], has received the required ground and flight training in [a glider or unpowered ultralight vehicle, as applicable]. I have determined that [he or she] is proficient in the techniques and procedures essential to the safe towing of [gliders or unpowered vehicles, as applicable] including airspeed limitations; emergency procedures; signals used; and maximum angles of bank. -- 15 of 18 -- 8/27/18 \tAC 61-65H Appendix A A-21",
    "category": "Additional Endorsements",
    "expires": false,
    "lines": [
      "A.81 \tGlider and unpowered ultralight vehicle towing ground and flight: § 61.69(a)(3).",
      "I certify that [First name, MI, Last name], [grade of pilot certificate], [certificate number],",
      "has received the required ground and flight training in [a glider or unpowered ultralight",
      "vehicle, as applicable]. I have determined that [he or she] is proficient in the techniques",
      "and procedures essential to the safe towing of [gliders or unpowered vehicles, as",
      "applicable] including airspeed limitations; emergency procedures; signals used; and",
      "maximum angles of bank.",
      "-- 15 of 18 --",
      "8/27/18 \tAC 61-65H",
      "Appendix A",
      "A-21"
    ]
  },
  {
    "number": "A.82",
    "title": "Review of a home study curriculum: § 61.35(a)(1).",
    "section": {
      "id": "additional-student-pilot",
      "title": "SPORT OR RECREATIONAL PILOT CERTIFICATES"
    },
    "farReference": null,
    "endorsementText": "I certify I have reviewed the home study curriculum of [First name, MI, Last name]. I have determined that [he or she] is prepared for the [name of] knowledge test. Note: This endorsement cannot be used for the ATP Airplane Multiengine Knowledge Test.",
    "category": "Additional Endorsements",
    "expires": false,
    "lines": [
      "A.82 \tReview of a home study curriculum: § 61.35(a)(1).",
      "I certify I have reviewed the home study curriculum of [First name, MI, Last name].",
      "I have determined that [he or she] is prepared for the [name of] knowledge test.",
      "Note: This endorsement cannot be used for the ATP Airplane Multiengine",
      "Knowledge Test."
    ]
  },
  {
    "number": "A.83",
    "title": "Experimental aircraft only—additional aircraft category or class rating (other than",
    "section": {
      "id": "additional-student-pilot",
      "title": "SPORT OR RECREATIONAL PILOT CERTIFICATES"
    },
    "farReference": "§ 61.63(h).",
    "endorsementText": "I certify that [First name, MI, Last name], [grade of pilot certificate], [certificate number], as required by § 61.63(h), is proficient to act as pilot in command in a [category, class, make, and model] of experimental aircraft and has logged at least 5 hours flight time logged between September 1, 2004, and August 31, 2005, while acting as pilot in command in [aircraft category/class rating and make and model] that has been issued an experimental certificate.",
    "category": "Additional Endorsements",
    "expires": false,
    "lines": [
      "A.83 \tExperimental aircraft only—additional aircraft category or class rating (other than",
      "I certify that [First name, MI, Last name], [grade of pilot certificate], [certificate number],",
      "as required by § 61.63(h), is proficient to act as pilot in command in a [category, class,",
      "make, and model] of experimental aircraft and has logged at least 5 hours flight time",
      "logged between September 1, 2004, and August 31, 2005, while acting as pilot in",
      "command in [aircraft category/class rating and make and model] that has been issued an",
      "experimental certificate."
    ]
  },
  {
    "number": "A.84",
    "title": "Experimental aircraft only—additional aircraft category or class rating ATP:",
    "section": {
      "id": "additional-student-pilot",
      "title": "SPORT OR RECREATIONAL PILOT CERTIFICATES"
    },
    "farReference": "§ 61.65(g).",
    "endorsementText": "I certify that [First name, MI, Last name], [grade of pilot certificate], [certificate number], as required by § 61.65(g) is proficient to act as pilot in command in a [category, class, make, and model] of experimental aircraft and has logged at least 5 hours flight time logged between September 1, 2004, and August 31, 2005, while acting as pilot in command in [aircraft category/class rating and make and model] that has been issued an experimental certificate.",
    "category": "Additional Endorsements",
    "expires": false,
    "lines": [
      "A.84 \tExperimental aircraft only—additional aircraft category or class rating ATP:",
      "I certify that [First name, MI, Last name], [grade of pilot certificate], [certificate number],",
      "as required by § 61.65(g) is proficient to act as pilot in command in a [category, class,",
      "make, and model] of experimental aircraft and has logged at least 5 hours flight time",
      "logged between September 1, 2004, and August 31, 2005, while acting as pilot in",
      "command in [aircraft category/class rating and make and model] that has been issued an",
      "experimental certificate."
    ]
  },
  {
    "number": "A.85",
    "title": "Aeronautical experience credit—ultralight vehicles: § 61.52.",
    "section": {
      "id": "additional-student-pilot",
      "title": "SPORT OR RECREATIONAL PILOT CERTIFICATES"
    },
    "farReference": "§ 61.52(c). I have determined that ",
    "endorsementText": "I certify that I have reviewed the records of [First name, MI, Last name], as required by § 61.52(c). I have determined that [he or she] may use [number of hours] aeronautical experience obtained in an ultralight vehicle to meet the requirements for [certificate/rating/privilege]. NIGHT VISION GOGGLES (NVG) OPERATIONS",
    "category": "Additional Endorsements",
    "expires": false,
    "lines": [
      "A.85 \tAeronautical experience credit—ultralight vehicles: § 61.52.",
      "I certify that I have reviewed the records of [First name, MI, Last name], as required by",
      "§ 61.52(c). I have determined that [he or she] may use [number of hours] aeronautical",
      "experience obtained in an ultralight vehicle to meet the requirements for",
      "[certificate/rating/privilege].",
      "NIGHT VISION GOGGLES (NVG) OPERATIONS"
    ]
  },
  {
    "number": "A.86",
    "title": "Endorsement required for ground training to act as pilot in command of an aircraft",
    "section": {
      "id": "additional-student-pilot",
      "title": "SPORT OR RECREATIONAL PILOT CERTIFICATES"
    },
    "farReference": "§ 61.31(k)(1). This training and endorsement must be given by an",
    "endorsementText": "I certify that [First name, MI, Last name], [grade of pilot certificate], [certificate number], has received the ground training required by § 61.31(k)(1), (i) through (v) to conduct night vision goggle operations. -- 16 of 18 -- 8/27/18 \tAC 61-65H Appendix A A-22",
    "category": "Additional Endorsements",
    "expires": false,
    "lines": [
      "A.86 \tEndorsement required for ground training to act as pilot in command of an aircraft",
      "I certify that [First name, MI, Last name], [grade of pilot certificate], [certificate number],",
      "has received the ground training required by § 61.31(k)(1), (i) through (v) to conduct",
      "night vision goggle operations.",
      "-- 16 of 18 --",
      "8/27/18 \tAC 61-65H",
      "Appendix A",
      "A-22"
    ]
  },
  {
    "number": "A.87",
    "title": "Endorsement required for flight training and statement of proficiency to act as pilot",
    "section": {
      "id": "additional-student-pilot",
      "title": "SPORT OR RECREATIONAL PILOT CERTIFICATES"
    },
    "farReference": "§ 61.31(k)(2). This training and endorsement",
    "endorsementText": "I certify that [First name, MI, Last name], [grade of pilot certificate], [certificate number], has received the flight training on night vision goggle operations required by 14 CFR § 61.31(k)(2), (i) through (iv). I find [he or she] proficient in the use of night vision goggles.",
    "category": "Additional Endorsements",
    "expires": false,
    "lines": [
      "A.87 \tEndorsement required for flight training and statement of proficiency to act as pilot",
      "I certify that [First name, MI, Last name], [grade of pilot certificate], [certificate number],",
      "has received the flight training on night vision goggle operations required by 14 CFR",
      "§ 61.31(k)(2), (i) through (iv). I find [he or she] proficient in the use of night vision",
      "goggles."
    ]
  },
  {
    "number": "A.88",
    "title": "Endorsement required to provide training for NVG operations: § 61.195(k)(7).",
    "section": {
      "id": "additional-student-pilot",
      "title": "SPORT OR RECREATIONAL PILOT CERTIFICATES"
    },
    "farReference": "§ 61.195(k) and is authorized to perform",
    "endorsementText": "I certify that [First name, MI, Last name], holder of CFI Certificate No. [ \t], meets the night vision goggle instructor requirements of § 61.195(k) and is authorized to perform the night vision goggle pilot-in-command qualification and recent flight experience requirements under §§ 61.31(k) and 61.57(f) and (g). This endorsement does not provide the authority to endorse another flight instructor as a night vision goggle instructor. /s/ [date] I. M. Inspector 987654321CFI Exp. 12-31-19 Position ENHANCED FLIGHT VISION SYSTEM (EFVS)",
    "category": "Additional Endorsements",
    "expires": false,
    "lines": [
      "A.88 \tEndorsement required to provide training for NVG operations: § 61.195(k)(7).",
      "I certify that [First name, MI, Last name], holder of CFI Certificate No. [ \t], meets the",
      "night vision goggle instructor requirements of § 61.195(k) and is authorized to perform",
      "the night vision goggle pilot-in-command qualification and recent flight experience",
      "requirements under §§ 61.31(k) and 61.57(f) and (g). This endorsement does not provide",
      "the authority to endorse another flight instructor as a night vision goggle instructor.",
      "/s/ [date] I. M. Inspector 987654321CFI Exp. 12-31-19 Position",
      "ENHANCED FLIGHT VISION SYSTEM (EFVS)"
    ]
  },
  {
    "number": "A.89",
    "title": "Endorsement for EFVS ground training: § 61.66(a).",
    "section": {
      "id": "additional-student-pilot",
      "title": "SPORT OR RECREATIONAL PILOT CERTIFICATES"
    },
    "farReference": "§ 61.66(a) appropriate to the",
    "endorsementText": "I certify that [First name, MI, Last name], [pilot certificate], [certificate number], has satisfactorily completed the ground training required by § 61.66(a) appropriate to the [appropriate aircraft category] category of aircraft.",
    "category": "Additional Endorsements",
    "expires": false,
    "lines": [
      "A.89 \tEndorsement for EFVS ground training: § 61.66(a).",
      "I certify that [First name, MI, Last name], [pilot certificate], [certificate number], has",
      "satisfactorily completed the ground training required by § 61.66(a) appropriate to the",
      "[appropriate aircraft category] category of aircraft."
    ]
  },
  {
    "number": "A.90",
    "title": "Endorsement for EFVS flight training: § 61.66(b).",
    "section": {
      "id": "additional-student-pilot",
      "title": "SPORT OR RECREATIONAL PILOT CERTIFICATES"
    },
    "farReference": "§ 61.66(b) and is proficient in the use of EFVS in",
    "endorsementText": "I certify that [First name, MI, Last name], [pilot certificate], [certificate number], has received the flight training required by § 61.66(b) and is proficient in the use of EFVS in the [appropriate aircraft category in which the flight training was conducted] category of aircraft for EFVS operations conducted under [§ 91.176(a), (b), or both § 91.176(a) and (b)].",
    "category": "Additional Endorsements",
    "expires": false,
    "lines": [
      "A.90 \tEndorsement for EFVS flight training: § 61.66(b).",
      "I certify that [First name, MI, Last name], [pilot certificate], [certificate number], has",
      "received the flight training required by § 61.66(b) and is proficient in the use of EFVS in",
      "the [appropriate aircraft category in which the flight training was conducted] category of",
      "aircraft for EFVS operations conducted under [§ 91.176(a), (b), or both § 91.176(a)",
      "and (b)]."
    ]
  },
  {
    "number": "A.91",
    "title": "Endorsement for EFVS ground and flight training: § 61.66(a) and (b).",
    "section": {
      "id": "additional-student-pilot",
      "title": "SPORT OR RECREATIONAL PILOT CERTIFICATES"
    },
    "farReference": "§ 61.66(a) and has received the",
    "endorsementText": "I certify that [First name, MI, Last name], [pilot certificate], [certificate number], has satisfactorily completed the ground training required by § 61.66(a) and has received the flight training required by § 61.66(b) for EFVS operations and is proficient in the use of EFVS in the [appropriate aircraft category in which the ground and flight training was conducted] category of aircraft for EFVS operations conducted under [§ 91.176(a), (b), or both § 91.176(a) and (b)]. -- 17 of 18 -- 8/27/18 \tAC 61-65H Appendix A A-23",
    "category": "Additional Endorsements",
    "expires": false,
    "lines": [
      "A.91 \tEndorsement for EFVS ground and flight training: § 61.66(a) and (b).",
      "I certify that [First name, MI, Last name], [pilot certificate], [certificate number], has",
      "satisfactorily completed the ground training required by § 61.66(a) and has received the",
      "flight training required by § 61.66(b) for EFVS operations and is proficient in the use of",
      "EFVS in the [appropriate aircraft category in which the ground and flight training was",
      "conducted] category of aircraft for EFVS operations conducted under [§ 91.176(a), (b), or",
      "both § 91.176(a) and (b)].",
      "-- 17 of 18 --",
      "8/27/18 \tAC 61-65H",
      "Appendix A",
      "A-23"
    ]
  },
  {
    "number": "A.92",
    "title": "Endorsement for EFVS supplementary training: § 61.66(c).",
    "section": {
      "id": "additional-student-pilot",
      "title": "SPORT OR RECREATIONAL PILOT CERTIFICATES"
    },
    "farReference": "§ 61.66(c) for",
    "endorsementText": "I certify that [First name, MI, Last name], [pilot certificate], [certificate number], has satisfactorily completed the required ground and flight training required by § 61.66(c) for EFVS operations and is proficient in the use of EFVS in the [the appropriate aircraft category in which the supplementary ground and flight training was conducted] category of aircraft for EFVS operations conducted under [§ 91.176(a), (b), or both § 91.176(a) and (b)]. -- 18 of 18 --",
    "category": "Additional Endorsements",
    "expires": false,
    "lines": [
      "A.92 \tEndorsement for EFVS supplementary training: § 61.66(c).",
      "I certify that [First name, MI, Last name], [pilot certificate], [certificate number], has",
      "satisfactorily completed the required ground and flight training required by § 61.66(c) for",
      "EFVS operations and is proficient in the use of EFVS in the [the appropriate aircraft",
      "category in which the supplementary ground and flight training was conducted] category",
      "of aircraft for EFVS operations conducted under [§ 91.176(a), (b), or both § 91.176(a)",
      "and (b)].",
      "-- 18 of 18 --"
    ]
  }
]